LICENSE.md
MANIFEST.in
README.md
requirements.txt
setup.py
drf_rbac/__init__.py
drf_rbac/admin.py
drf_rbac/apps.py
drf_rbac/authorization.py
drf_rbac/models.py
drf_rbac/settings.py
drf_rbac/urls.py
drf_rbac/views.py
drf_rbac/management/__init__.py
drf_rbac/management/commands/__init__.py
drf_rbac/management/commands/pinout.py
drf_rbac/migrations/0001_initial.py
drf_rbac/migrations/0002_auto_20221118_0826.py
drf_rbac/migrations/0003_auto_20221118_0835.py
drf_rbac/migrations/__init__.py
drf_rbac_plus.egg-info/PKG-INFO
drf_rbac_plus.egg-info/SOURCES.txt
drf_rbac_plus.egg-info/dependency_links.txt
drf_rbac_plus.egg-info/requires.txt
drf_rbac_plus.egg-info/top_level.txt