Metadata-Version: 2.1
Name: drf-rbac-plus
Version: 1.3.1
Summary: rbac permission plus
Home-page: https://github.com/MangoodLuck/drf-rbac-plus.git
Author: Xiao Man
Author-email: cloudbye@163.com
Maintainer: Xiao Man
Maintainer-email: cloudbye@163.com
License: MIT
Platform: linux
Requires-Python: >=3.5
License-File: LICENSE.md
